{"levelWidth":50,"mapEtc":{"45":{"type":1,"coords":[27,9]}},"mapSections":{},"mapLayout":{"0":{"rotation":0,"textureId":1,"type":"full","coords":[7,2]},"1":{"rotation":0,"textureId":1,"type":"full","coords":[43,2]},"2":{"rotation":0,"textureId":1,"type":"full","coords":[46,2]},"3":{"rotation":0,"textureId":1,"type":"full","coords":[21,3]},"4":{"rotation":0,"textureId":1,"type":"full","coords":[15,5]},"5":{"rotation":0,"textureId":1,"type":"full","coords":[26,5]},"6":{"rotation":0,"textureId":1,"type":"full","coords":[30,5]},"7":{"rotation":0,"textureId":1,"type":"full","coords":[11,6]},"8":{"rotation":0,"textureId":1,"type":"full","coords":[23,7]},"9":{"rotation":0,"textureId":1,"type":"full","coords":[27,7]},"10":{"rotation":0,"textureId":1,"type":"full","coords":[36,7]},"11":{"rotation":0,"textureId":1,"type":"full","coords":[41,7]},"12":{"rotation":0,"textureId":1,"type":"full","coords":[4,8]},"13":{"rotation":0,"textureId":1,"type":"full","coords":[18,8]},"14":{"rotation":0,"textureId":1,"type":"full","coords":[27,8]},"15":{"rotation":0,"textureId":1,"type":"full","coords":[12,9]},"16":{"rotation":0,"textureId":1,"type":"full","coords":[48,9]},"17":{"rotation":0,"textureId":1,"type":"full","coords":[20,10]},"18":{"rotation":0,"textureId":1,"type":"full","coords":[31,10]},"19":{"rotation":0,"textureId":1,"type":"full","coords":[18,11]},"20":{"rotation":0,"textureId":1,"type":"full","coords":[19,11]},"21":{"rotation":0,"textureId":1,"type":"full","coords":[37,11]},"22":{"rotation":0,"textureId":1,"type":"full","coords":[5,12]},"23":{"rotation":0,"textureId":1,"type":"full","coords":[7,12]},"24":{"rotation":0,"textureId":1,"type":"full","coords":[8,12]},"25":{"rotation":0,"textureId":1,"type":"full","coords":[10,12]},"26":{"rotation":0,"textureId":1,"type":"full","coords":[13,12]},"27":{"rotation":0,"textureId":1,"type":"full","coords":[15,12]},"28":{"rotation":0,"textureId":1,"type":"full","coords":[24,12]},"29":{"rotation":0,"textureId":1,"type":"full","coords":[23,13]},"30":{"rotation":0,"textureId":1,"type":"full","coords":[29,13]},"31":{"rotation":0,"textureId":1,"type":"full","coords":[9,14]},"32":{"rotation":0,"textureId":1,"type":"full","coords":[49,14]},"33":{"rotation":0,"textureId":1,"type":"full","coords":[2,15]},"34":{"rotation":0,"textureId":1,"type":"full","coords":[26,15]},"35":{"rotation":0,"textureId":1,"type":"full","coords":[32,15]},"36":{"rotation":0,"textureId":1,"type":"full","coords":[34,15]},"37":{"rotation":0,"textureId":1,"type":"full","coords":[10,17]},"38":{"rotation":0,"textureId":1,"type":"full","coords":[38,17]},"39":{"rotation":0,"textureId":1,"type":"full","coords":[45,18]},"40":{"rotation":0,"textureId":1,"type":"full","coords":[1,19]},"41":{"rotation":0,"textureId":1,"type":"full","coords":[11,19]},"42":{"rotation":0,"textureId":1,"type":"full","coords":[0,20]},"43":{"rotation":0,"textureId":1,"type":"full","coords":[20,20]},"44":{"rotation":0,"textureId":1,"type":"full","coords":[30,22]}},"levelHeight":25,"mapEntities":{}}